fastapi3/__init__.py
fastapi3/__main__.py
fastapi3/_compat.py
fastapi3/applications.py
fastapi3/background.py
fastapi3/cli.py
fastapi3/concurrency.py
fastapi3/config.py
fastapi3/datastructures.py
fastapi3/dependencies/__init__.py
fastapi3/dependencies/models.py
fastapi3/dependencies/utils.py
fastapi3/encoders.py
fastapi3/exception_handlers.py
fastapi3/exceptions.py
fastapi3/logger.py
fastapi3/middleware/__init__.py
fastapi3/middleware/cors.py
fastapi3/middleware/gzip.py
fastapi3/middleware/httpsredirect.py
fastapi3/middleware/trustedhost.py
fastapi3/middleware/wsgi.py
fastapi3/openapi/__init__.py
fastapi3/openapi/constants.py
fastapi3/openapi/docs.py
fastapi3/openapi/models.py
fastapi3/openapi/utils.py
fastapi3/param_functions.py
fastapi3/params.py
fastapi3/requests.py
fastapi3/responses.py
fastapi3/routing.py
fastapi3/security/__init__.py
fastapi3/security/api_key.py
fastapi3/security/base.py
fastapi3/security/http.py
fastapi3/security/oauth2.py
fastapi3/security/open_id_connect_url.py
fastapi3/security/utils.py
fastapi3/static/favicon.png
fastapi3/static/redoc.standalone.js
fastapi3/static/swagger-ui-bundle.js
fastapi3/static/swagger-ui.css
fastapi3/staticfiles.py
fastapi3/templating.py
fastapi3/testclient.py
fastapi3/types.py
fastapi3/utils.py
fastapi3/websockets.py
fastapi3-0.1.4.dist-info/LICENSE
fastapi3-0.1.4.dist-info/METADATA
fastapi3-0.1.4.dist-info/WHEEL
fastapi3-0.1.4.dist-info/RECORD
