Metadata-Version: 2.1
Name: fastapi3
Version: 0.1.4
Summary: fastapi的国产化替代品
Author: zhangdapeng
Author-email: 1156956636@qq.com
Requires-Python: >=3.12,<4.0
Classifier: Programming Language :: Python :: 3
Classifier: Programming Language :: Python :: 3.12
Classifier: Programming Language :: Python :: 3.13
Requires-Dist: pydantic (>=2.10.5,<3.0.0)
Requires-Dist: starlette (>=0.45.2,<0.46.0)
Requires-Dist: uvicorn3 (>=0.1.2,<0.2.0)
